dflat/__init__.py
dflat/GDSII/__init__.py
dflat/GDSII/assemble.py
dflat/GDSII/gds_utils.py
dflat/initialize/__init__.py
dflat/initialize/interleave.py
dflat/initialize/lenses.py
dflat/metasurface/__init__.py
dflat/metasurface/datasets.py
dflat/metasurface/latent.py
dflat/metasurface/load_utils.py
dflat/metasurface/nn.py
dflat/metasurface/nn_siren.py
dflat/metasurface/optical_model.py
dflat/metasurface/reverse_lookup.py
dflat/metasurface/trainer.py
dflat/plot_utilities/__init__.py
dflat/plot_utilities/mp_format.py
dflat/plot_utilities/vis.py
dflat/propagation/__init__.py
dflat/propagation/propagators.py
dflat/propagation/propagators_legacy.py
dflat/propagation/util.py
dflat/radial_tranforms/__init__.py
dflat/radial_tranforms/hankel_ops.py
dflat/radial_tranforms/radial_ops.py
dflat/rcwa/__init__.py
dflat/rcwa/colburn_rcwa_utils.py
dflat/rcwa/colburn_tensor_utils.py
dflat/rcwa/material_utils.py
dflat/rcwa/rcwa_solver.py
dflat/render/__init__.py
dflat/render/fft_convolve.py
dflat/render/fronto_planar_renderer.py
dflat/render/util_meas.py
dflat/render/util_sensor.py
dflat/render/util_spectral.py
dflat_opt-4.3.dist-info/licenses/LICENSE
dflat_opt-4.3.dist-info/METADATA
dflat_opt-4.3.dist-info/WHEEL
dflat_opt-4.3.dist-info/top_level.txt
dflat_opt-4.3.dist-info/RECORD
