Metadata-Version: 2.4
Name: dflat_opt
Version: 4.3
Summary: D-Flat is a forward and inverse design framework for flat optics. Although specially geared for the design of metasurfaces, it may be used broadly for end-to-end imaging and sensing task.
Home-page: https://github.com/DeanHazineh/DFlat
Author: Dean Hazineh
Author-email: dhazineh@g.harvard.edu
Classifier: License :: OSI Approved :: GNU General Public License v3 (GPLv3)
License-File: LICENSE
Requires-Dist: pytest
Requires-Dist: pytest-cov
Requires-Dist: requests
Requires-Dist: setuptools
Requires-Dist: numpy
Requires-Dist: scipy
Requires-Dist: matplotlib
Requires-Dist: moviepy
Requires-Dist: pyhank
Requires-Dist: einops
Requires-Dist: tqdm
Requires-Dist: pandas
Requires-Dist: opencv-python
Requires-Dist: gdspy
Requires-Dist: mat73
Requires-Dist: omegaconf
Requires-Dist: natsort
Provides-Extra: docs
Requires-Dist: sphinx; extra == "docs"
Requires-Dist: sphinx_rtd_theme; extra == "docs"
Requires-Dist: sphinx-design; extra == "docs"
Dynamic: license-file
